unigo/__init__.py
unigo/__main__.py
unigo/api/data_objects.py
unigo/api/io.py
unigo/api/pwas.py
unigo/api/store/__init__.py
unigo/api/store/cache/__init__.py
unigo/api/store/cache/local.py
unigo/api/store/cache/redis.py
unigo/api/store/client/__init__.py
unigo/api/store/client/mutators.py
unigo/api/store/client/viewers.py
unigo/api/test.py
unigo/command_line.py
unigo/data/go.owl.gz
unigo/data/uniprot-proteome_UP000000807.xml.gz
unigo/repl/__init__.py
unigo/repl/commands/__init__.py
unigo/repl/commands/connect.py
unigo/repl/commands/mutators.py
unigo/repl/commands/viewers.py
unigo/repl/helpers.py
unigo/stats/clustering.py
unigo/stats/ora.py
unigo/test/__init__.py
unigo/test/pwas.py
unigo/test/test_time.py
unigo/test/test_time.py.lprof
unigo/test/timing.txt
unigo/test/timing_cython.txt
unigo/tree/__init__.py
unigo/tree/heap.py
unigo/tree/node.py
unigo/utils/api.py
unigo/utils/io.py
unigo/utils/uniprot.py
unigo-2.1.0.dist-info/LICENSE
unigo-2.1.0.dist-info/WHEEL
unigo-2.1.0.dist-info/METADATA
unigo-2.1.0.dist-info/RECORD
