Metadata-Version: 2.1
Name: unigo
Version: 2.1.0
Summary: 
License: BSD
Author: glaunay
Author-email: pitooon@gmail.com
Requires-Python: >=3.8,<3.11
Classifier: License :: Other/Proprietary License
Classifier: Programming Language :: Python :: 3
Classifier: Programming Language :: Python :: 3.10
Classifier: Programming Language :: Python :: 3.8
Classifier: Programming Language :: Python :: 3.9
Requires-Dist: Cython (>=0.29.32,<0.30.0)
Requires-Dist: Flask (>=2.0.2,<3.0.0)
Requires-Dist: Owlready2 (>=0.38,<0.39)
Requires-Dist: docopt (>=0.6.2,<0.7.0)
Requires-Dist: line-profiler (>=3.5.1,<4.0.0)
Requires-Dist: marshmallow (>=3.14.1,<4.0.0)
Requires-Dist: notebook (>=6.4.12,<7.0.0)
Requires-Dist: pydantic (>=1.10.1,<2.0.0)
Requires-Dist: pyproteinsext (>=3.0.3,<4.0.0)
Requires-Dist: requests (>=2.27.1,<3.0.0)
Requires-Dist: requires (>=0.10.2,<0.11.0)
Requires-Dist: scipy (>=1.8.0,<2.0.0)
Requires-Dist: wheel (>=0.37.1,<0.38.0)
